hindsight/__init__.py
hindsight/server.py
hindsight_all-0.4.7.dist-info/METADATA
hindsight_all-0.4.7.dist-info/WHEEL
hindsight_all-0.4.7.dist-info/RECORD
