Metadata-Version: 2.4
Name: hindsight-all
Version: 0.4.7
Summary: Hindsight: Agent Memory That Works Like Human Memory - All-in-One Bundle
Requires-Python: >=3.11
Requires-Dist: hindsight-api>=0.0.7
Requires-Dist: hindsight-client>=0.0.7
Provides-Extra: test
Requires-Dist: pytest-asyncio>=0.21.0; extra == 'test'
Requires-Dist: pytest>=7.0.0; extra == 'test'
